README.md
setup.py
lambdapy/__init__.py
lambdapy/core.py
lambdapy/repl.py
lambdapy.egg-info/PKG-INFO
lambdapy.egg-info/SOURCES.txt
lambdapy.egg-info/dependency_links.txt
lambdapy.egg-info/entry_points.txt
lambdapy.egg-info/requires.txt
lambdapy.egg-info/top_level.txt