Metadata-Version: 1.2
Name: lambdapy
Version: 0.0.2
Summary: Untyped Lambda calculus in python
Home-page: UNKNOWN
Author: Jacob Jäger
Maintainer: Jacob Jäger
License: UNKNOWN
Platform: UNKNOWN
Classifier: Development Status :: 3 - Alpha
Classifier: License :: OSI Approved :: MIT License
Classifier: Natural Language :: English
Classifier: Operating System :: OS Independent
Classifier: Programming Language :: Python :: 3 :: Only
